lfs_cookie_consent/__init__.py
lfs_cookie_consent/apps.py
lfs_cookie_consent/urls.py
lfs_cookie_consent/views.py
lfs_cookie_consent-1.0.2.dist-info/licenses/LICENSE
lfs_cookie_consent-1.0.2.dist-info/METADATA
lfs_cookie_consent-1.0.2.dist-info/WHEEL
lfs_cookie_consent-1.0.2.dist-info/top_level.txt
lfs_cookie_consent-1.0.2.dist-info/RECORD
