Metadata-Version: 2.4
Name: lfs-cookie-consent
Version: 1.0.2
Summary: Cookie Consent App for LFS/Django
Author-email: Kai Diefenbach <kai.diefenbach@iqpp.de>
Requires-Python: <3.14,>=3.8
License-File: LICENSE
Requires-Dist: Django<6.0,>=3.2
Dynamic: license-file
